distributedlock/__init__.py
distributedlock/apps.py
distributedlock/cachelock.py
distributedlock/databaselock.py
distributedlock/lock.py
distributedlock/models.py
distributedlock/urls.py
distributedlock/views.py
distributedlock/migrations/0001_initial.py
distributedlock/migrations/0002_add_key_unique_index.py
distributedlock/migrations/__init__.py
django_distributedlock-0.5.0.dist-info/LICENSE
django_distributedlock-0.5.0.dist-info/METADATA
django_distributedlock-0.5.0.dist-info/WHEEL
django_distributedlock-0.5.0.dist-info/top_level.txt
django_distributedlock-0.5.0.dist-info/RECORD
