Metadata-Version: 2.1
Name: django-distributedlock
Version: 0.5.0
Summary: Distributed locking in Django
Home-page: https://github.com/15five/django-distributedlock
Author: Erik Rivera
Author-email: Erik Rivera <erik.river@gmail.com>
Maintainer: Paul Logston
Maintainer-email: Paul Logston <code@logston.me>
License: BSD
Project-URL: Homepage, https://github.com/15five/django-distributedlock
Keywords: distributed,lock
Classifier: Programming Language :: Python :: 3
Classifier: Topic :: Software Development :: Libraries :: Python Modules
Classifier: License :: OSI Approved :: BSD License
Classifier: Operating System :: OS Independent
Requires-Python: >=3.4
License-File: LICENSE
Provides-Extra: testing
Requires-Dist: django ; extra == 'testing'
Requires-Dist: gevent ; extra == 'testing'
